smile_datasets/__init__.py
smile_datasets/dataset.py
smile_datasets/utils.py
smile_datasets/mlm/__init__.py
smile_datasets/mlm/dataset.py
smile_datasets/mlm/example.py
smile_datasets/mlm/masking_strategy.py
smile_datasets/mlm/parsers.py
smile_datasets/mlm/readers.py
smile_datasets/question_answering/__init__.py
smile_datasets/question_answering/dataset.py
smile_datasets/question_answering/example.py
smile_datasets/question_answering/parsers.py
smile_datasets/question_answering/readers.py
smile_datasets/sequence_classification/__init__.py
smile_datasets/sequence_classification/dataset.py
smile_datasets/sequence_classification/example.py
smile_datasets/sequence_classification/parsers.py
smile_datasets/sequence_classification/readers.py
smile_datasets/simcse/__init__.py
smile_datasets/simcse/example.py
smile_datasets/simcse/hardneg_dataset.py
smile_datasets/simcse/parsers.py
smile_datasets/simcse/readers.py
smile_datasets/simcse/sup_dataset.py
smile_datasets/simcse/unsup_dataset.py
smile_datasets/token_classification/__init__.py
smile_datasets/token_classification/dataset.py
smile_datasets/token_classification/example.py
smile_datasets/token_classification/parsers.py
smile_datasets/token_classification/readers.py
smile_datasets/token_classification/tokenizers.py
tests/__init__.py
tests/mlm_tests/__init__.py
tests/mlm_tests/dataset_test.py
tests/question_answering_tests/__init__.py
tests/question_answering_tests/dataset_test.py
tests/sequence_classification_tests/__init__.py
tests/sequence_classification_tests/dataset_test.py
tests/simcse_tests/__init__.py
tests/simcse_tests/dataset_test.py
tests/token_classification_tests/__init__.py
tests/token_classification_tests/dataset_test.py
smile_datasets-0.0.6.dist-info/LICENSE
smile_datasets-0.0.6.dist-info/METADATA
smile_datasets-0.0.6.dist-info/WHEEL
smile_datasets-0.0.6.dist-info/top_level.txt
smile_datasets-0.0.6.dist-info/RECORD
