Metadata-Version: 2.1
Name: smile-datasets
Version: 0.0.6
Summary: La**S**t **mile** datasets: Use `tf.data` to solve the last mile data loading problem for tensorflow.
Home-page: https://github.com/luozhouyang/smile-datasets
Author: ZhouYang Luo
Author-email: zhouyang.luo@gmail.com
License: Apache Software License
Platform: UNKNOWN
Classifier: Programming Language :: Python :: 3
Classifier: Programming Language :: Python :: 3.5
Classifier: Programming Language :: Python :: 3.6
Classifier: Programming Language :: Python :: 3.7
Classifier: Programming Language :: Python :: 3.8
Classifier: Programming Language :: Python :: 3.9
Classifier: License :: OSI Approved :: Apache Software License
Classifier: Operating System :: OS Independent
Classifier: Topic :: Scientific/Engineering :: Artificial Intelligence
License-File: LICENSE
Requires-Dist: tokenizers
Requires-Dist: tensorflow
